{
"skeleton": {
	"hash": "mRAOMm+JzfKMmixEidB+M+mg2Jg",
	"spine": "3.8.99",
	"x": -352.16,
	"y": -324.03,
	"width": 767,
	"height": 714,
	"images": "./images/",
	"audio": "D:/12月/新建文件夹/动画/转盘抽奖"
},
"bones": [
	{ "name": "root" },
	{ "name": "xingxingshanshuo_00000", "parent": "root", "length": 24.19, "rotation": 90, "x": -24.72, "y": -216.31 }
],
"slots": [
	{ "name": "xingxingshanshuo_00000", "bone": "xingxingshanshuo_00000", "attachment": "xingxingshanshuo_00015" }
],
"skins": [
	{
		"name": "default",
		"attachments": {
			"xingxingshanshuo_00000": {
				"xingxingshanshuo_00000": { "x": -10.23, "y": 22.94, "rotation": -90, "width": 271, "height": 165 },
				"xingxingshanshuo_00001": { "x": -10.23, "y": 22.94, "rotation": -90, "width": 271, "height": 165 },
				"xingxingshanshuo_00002": { "x": -5.23, "y": 17.94, "rotation": -90, "width": 283, "height": 159 },
				"xingxingshanshuo_00003": { "x": -5.23, "y": 17.94, "rotation": -90, "width": 283, "height": 159 },
				"xingxingshanshuo_00004": { "x": -1.23, "y": 13.44, "rotation": -90, "width": 290, "height": 147 },
				"xingxingshanshuo_00005": { "x": -8.73, "y": -15.06, "rotation": -90, "width": 339, "height": 156 },
				"xingxingshanshuo_00006": { "x": -8.73, "y": -15.06, "rotation": -90, "width": 339, "height": 156 },
				"xingxingshanshuo_00007": { "x": -15.73, "y": -22.06, "rotation": -90, "width": 345, "height": 160 },
				"xingxingshanshuo_00008": { "x": -15.73, "y": -22.06, "rotation": -90, "width": 345, "height": 160 },
				"xingxingshanshuo_00009": { "x": -11.73, "y": -29.56, "rotation": -90, "width": 350, "height": 176 },
				"xingxingshanshuo_00010": { "x": -3.73, "y": -41.06, "rotation": -90, "width": 343, "height": 184 },
				"xingxingshanshuo_00011": { "x": -3.73, "y": -41.06, "rotation": -90, "width": 343, "height": 184 },
				"xingxingshanshuo_00012": { "x": 6.27, "y": -26.06, "rotation": -90, "width": 379, "height": 186 },
				"xingxingshanshuo_00013": { "x": 6.27, "y": -26.06, "rotation": -90, "width": 379, "height": 186 },
				"xingxingshanshuo_00014": { "x": 15.27, "y": -22.56, "rotation": -90, "width": 388, "height": 184 },
				"xingxingshanshuo_00015": { "x": 13.27, "y": -20.56, "rotation": -90, "width": 400, "height": 196 }
			}
		}
	}
],
"animations": {
	"animation": {
		"slots": {
			"xingxingshanshuo_00000": {
				"attachment": [
					{ "name": "xingxingshanshuo_00000" },
					{ "time": 0.0333, "name": "xingxingshanshuo_00001" },
					{ "time": 0.0667, "name": "xingxingshanshuo_00002" },
					{ "time": 0.1, "name": "xingxingshanshuo_00003" },
					{ "time": 0.1333, "name": "xingxingshanshuo_00004" },
					{ "time": 0.1667, "name": "xingxingshanshuo_00005" },
					{ "time": 0.2, "name": "xingxingshanshuo_00006" },
					{ "time": 0.2333, "name": "xingxingshanshuo_00007" },
					{ "time": 0.2667, "name": "xingxingshanshuo_00008" },
					{ "time": 0.3, "name": "xingxingshanshuo_00009" },
					{ "time": 0.3333, "name": "xingxingshanshuo_00010" },
					{ "time": 0.3667, "name": "xingxingshanshuo_00011" },
					{ "time": 0.4, "name": "xingxingshanshuo_00012" },
					{ "time": 0.4333, "name": "xingxingshanshuo_00013" },
					{ "time": 0.4667, "name": "xingxingshanshuo_00014" },
					{ "time": 0.5, "name": "xingxingshanshuo_00015" },
					{ "time": 0.5333, "name": "xingxingshanshuo_00000" },
					{ "time": 0.5667, "name": "xingxingshanshuo_00001" },
					{ "time": 0.6, "name": "xingxingshanshuo_00002" },
					{ "time": 0.6333, "name": "xingxingshanshuo_00003" },
					{ "time": 0.6667, "name": "xingxingshanshuo_00004" },
					{ "time": 0.7, "name": "xingxingshanshuo_00005" },
					{ "time": 0.7333, "name": "xingxingshanshuo_00006" },
					{ "time": 0.7667, "name": "xingxingshanshuo_00007" },
					{ "time": 0.8, "name": "xingxingshanshuo_00008" },
					{ "time": 0.8333, "name": "xingxingshanshuo_00009" },
					{ "time": 0.8667, "name": "xingxingshanshuo_00010" }
				]
			}
		}
	}
}
}